style/__init__.py
style/aimmslexer.py
aimms_pygments_style-2018.11.1.dist-info/LICENSE
aimms_pygments_style-2018.11.1.dist-info/METADATA
aimms_pygments_style-2018.11.1.dist-info/WHEEL
aimms_pygments_style-2018.11.1.dist-info/entry_points.txt
aimms_pygments_style-2018.11.1.dist-info/top_level.txt
aimms_pygments_style-2018.11.1.dist-info/RECORD
