Metadata-Version: 2.1
Name: aimms-pygments-style
Version: 2018.11.1
Summary: aimms-pygments-style is a colorful style for Pygments, especially adapted for AIMMS language
Home-page: https://gitlab.com/ArthurdHerbemont/aimms-pygments-style
Author: Arthur Herbemont
Author-email: arthur.dherbemont@aimms.com
License: GPLv2
Keywords: pygments syntax highlighting
Platform: UNKNOWN
Requires-Dist: pygments (>=2)
